{
  "timestamp": "Tue, May 20, 9:09 PM",
  "standings": [
    {
      "team": "LAD",
      "wins": 29,
      "losses": 19,
      "pct": ".604",
      "gb": "-",
      "streak": "L4",
      "last10": "4-6",
      "today": "vs AZ (live) @"
    },
    {
      "team": "SD",
      "wins": 27,
      "losses": 19,
      "pct": ".587",
      "gb": "1.0",
      "streak": "L4",
      "last10": "4-6",
      "today": "L at TOR @"
    },
    {
      "team": "SF",
      "wins": 28,
      "losses": 20,
      "pct": ".583",
      "gb": "1.0",
      "streak": "L1",
      "last10": "4-6",
      "today": "vs KC (live) @"
    },
    {
      "team": "AZ",
      "wins": 26,
      "losses": 22,
      "pct": ".542",
      "gb": "3.0",
      "streak": "W2",
      "last10": "6-4",
      "today": "at LAD (live) @"
    },
    {
      "team": "COL",
      "wins": 8,
      "losses": 40,
      "pct": ".167",
      "gb": "21.0",
      "streak": "L3",
      "last10": "2-8",
      "today": "L vs PHI @"
    }
  ]
}