{
  "timestamp": "Sun, Aug 3, 1:08 PM",
  "standings": [
    {
      "team": "LAD",
      "wins": 65,
      "losses": 47,
      "pct": ".580",
      "gb": "-",
      "streak": "W1",
      "last10": "6-4",
      "today": "W at TB @"
    },
    {
      "team": "SD",
      "wins": 61,
      "losses": 50,
      "pct": ".550",
      "gb": "3.5",
      "streak": "L1",
      "last10": "6-4",
      "today": "vs STL @ 1:10"
    },
    {
      "team": "SF",
      "wins": 55,
      "losses": 56,
      "pct": ".495",
      "gb": "9.5",
      "streak": "L1",
      "last10": "3-7",
      "today": "at NYM (live) @"
    },
    {
      "team": "AZ",
      "wins": 52,
      "losses": 59,
      "pct": ".468",
      "gb": "12.5",
      "streak": "W1",
      "last10": "2-8",
      "today": "at ATH @ 1:05"
    },
    {
      "team": "COL",
      "wins": 30,
      "losses": 80,
      "pct": ".273",
      "gb": "34.0",
      "streak": "W2",
      "last10": "6-4",
      "today": "vs PIT (live) @"
    }
  ]
}