{
  "timestamp": "Sat, Sep 27, 5:34 PM",
  "standings": [
    {
      "team": "LAD",
      "wins": 91,
      "losses": 69,
      "pct": ".569",
      "gb": "-",
      "streak": "W3",
      "last10": "7-3",
      "today": "at SEA @ 6:40"
    },
    {
      "team": "SD",
      "wins": 88,
      "losses": 72,
      "pct": ".550",
      "gb": "3.0",
      "streak": "W1",
      "last10": "6-4",
      "today": "vs AZ @ 5:40"
    },
    {
      "team": "AZ",
      "wins": 80,
      "losses": 80,
      "pct": ".500",
      "gb": "11.0",
      "streak": "L3",
      "last10": "5-5",
      "today": "at SD @ 5:40"
    },
    {
      "team": "SF",
      "wins": 80,
      "losses": 81,
      "pct": ".497",
      "gb": "11.5",
      "streak": "W3",
      "last10": "5-5",
      "today": "W vs COL @"
    },
    {
      "team": "COL",
      "wins": 43,
      "losses": 118,
      "pct": ".267",
      "gb": "48.5",
      "streak": "L5",
      "last10": "2-8",
      "today": "L at SF @"
    }
  ]
}