{
  "timestamp": "Sat, Jul 18, 1:19 PM",
  "standings": [
    {
      "team": "LAD",
      "wins": 62,
      "losses": 36,
      "pct": ".633",
      "gb": "-",
      "streak": "W1",
      "last10": "5-5",
      "today": "at NYY @ 5:08"
    },
    {
      "team": "AZ",
      "wins": 49,
      "losses": 48,
      "pct": ".505",
      "gb": "12.5",
      "streak": "L1",
      "last10": "6-4",
      "today": "vs STL @ 1:10"
    },
    {
      "team": "SD",
      "wins": 48,
      "losses": 49,
      "pct": ".495",
      "gb": "13.5",
      "streak": "L1",
      "last10": "5-5",
      "today": "at KC (live)"
    },
    {
      "team": "SF",
      "wins": 42,
      "losses": 55,
      "pct": ".433",
      "gb": "19.5",
      "streak": "W3",
      "last10": "6-4",
      "today": "at SEA @ 5:08"
    },
    {
      "team": "COL",
      "wins": 39,
      "losses": 60,
      "pct": ".394",
      "gb": "23.5",
      "streak": "L3",
      "last10": "3-7",
      "today": "vs CIN (live)"
    }
  ]
}